py.typed
orq_rc_poc2/__init__.py
orq_rc_poc2/_hooks/__init__.py
orq_rc_poc2/_hooks/registration.py
orq_rc_poc2/_hooks/sdkhooks.py
orq_rc_poc2/_hooks/types.py
orq_rc_poc2/_version.py
orq_rc_poc2/basesdk.py
orq_rc_poc2/contacts.py
orq_rc_poc2/deployments_sdk.py
orq_rc_poc2/feedback.py
orq_rc_poc2/files.py
orq_rc_poc2/httpclient.py
orq_rc_poc2/langchain/__init__.py
orq_rc_poc2/metrics.py
orq_rc_poc2/models/__init__.py
orq_rc_poc2/models/apierror.py
orq_rc_poc2/models/bulkfileuploadop.py
orq_rc_poc2/models/createcontactop.py
orq_rc_poc2/models/createfeedbackop.py
orq_rc_poc2/models/createpromptop.py
orq_rc_poc2/models/createpromptversionop.py
orq_rc_poc2/models/deletepromptop.py
orq_rc_poc2/models/deploymentcreatemetricop.py
orq_rc_poc2/models/deploymentgetconfigop.py
orq_rc_poc2/models/deploymentinvokeop.py
orq_rc_poc2/models/deployments.py
orq_rc_poc2/models/deploymentsop.py
orq_rc_poc2/models/duplicatepromptop.py
orq_rc_poc2/models/fileuploadop.py
orq_rc_poc2/models/findonepromptsnippetop.py
orq_rc_poc2/models/getallpromptsop.py
orq_rc_poc2/models/getallprompttemplatesop.py
orq_rc_poc2/models/getonepromptop.py
orq_rc_poc2/models/honoapierror.py
orq_rc_poc2/models/invaliddeploymentop.py
orq_rc_poc2/models/remoteconfigsgetconfigop.py
orq_rc_poc2/models/security.py
orq_rc_poc2/models/updatepromptop.py
orq_rc_poc2/prompt.py
orq_rc_poc2/prompts.py
orq_rc_poc2/py.typed
orq_rc_poc2/remoteconfig.py
orq_rc_poc2/sdk.py
orq_rc_poc2/sdkconfiguration.py
orq_rc_poc2/snippets.py
orq_rc_poc2/templates.py
orq_rc_poc2/types/__init__.py
orq_rc_poc2/types/basemodel.py
orq_rc_poc2/utils/__init__.py
orq_rc_poc2/utils/annotations.py
orq_rc_poc2/utils/enums.py
orq_rc_poc2/utils/eventstreaming.py
orq_rc_poc2/utils/forms.py
orq_rc_poc2/utils/headers.py
orq_rc_poc2/utils/logger.py
orq_rc_poc2/utils/metadata.py
orq_rc_poc2/utils/queryparams.py
orq_rc_poc2/utils/requestbodies.py
orq_rc_poc2/utils/retries.py
orq_rc_poc2/utils/security.py
orq_rc_poc2/utils/serializers.py
orq_rc_poc2/utils/url.py
orq_rc_poc2-0.0.26.dist-info/METADATA
orq_rc_poc2-0.0.26.dist-info/WHEEL
orq_rc_poc2-0.0.26.dist-info/RECORD
